oceanspy/__init__.py
oceanspy/_oceandataset.py
oceanspy/_ospy_utils.py
oceanspy/animate.py
oceanspy/compute.py
oceanspy/llc_rearrange.py
oceanspy/open_oceandataset.py
oceanspy/plot.py
oceanspy/subsample.py
oceanspy/utils.py
oceanspy/version.py
oceanspy/tests/conftest.py
oceanspy/tests/test_animate.py
oceanspy/tests/test_compute_calculus.py
oceanspy/tests/test_compute_functions.py
oceanspy/tests/test_llc_rearrange.py
oceanspy/tests/test_oceandataset.py
oceanspy/tests/test_open_oceandataset.py
oceanspy/tests/test_plot.py
oceanspy/tests/test_subsample.py
oceanspy/tests/test_utils.py
oceanspy/tests/test_version.py
oceanspy-0.3.5.dist-info/LICENSE
oceanspy-0.3.5.dist-info/METADATA
oceanspy-0.3.5.dist-info/WHEEL
oceanspy-0.3.5.dist-info/top_level.txt
oceanspy-0.3.5.dist-info/RECORD
