Metadata-Version: 2.1
Name: oceanspy
Version: 0.3.5
Summary: A Python package to facilitate ocean model data analysis and visualization.
License: MIT License
Classifier: Development Status :: 4 - Beta
Classifier: Intended Audience :: Science/Research
Classifier: License :: OSI Approved :: MIT License
Classifier: Operating System :: OS Independent
Classifier: Programming Language :: Python
Classifier: Programming Language :: Python :: 3
Classifier: Programming Language :: Python :: 3.9
Classifier: Programming Language :: Python :: 3.10
Classifier: Programming Language :: Python :: 3.11
Classifier: Topic :: Scientific/Engineering
Requires-Python: >=3.9
License-File: LICENSE
Requires-Dist: dask
Requires-Dist: xarray >=0.14.1
Requires-Dist: xgcm >=0.2.0
Requires-Dist: shapely
